examples/__init__.py
examples/attribute_formatters.py
examples/cdata_example.py
examples/complex_predicates.py
examples/complex_predicates_usage.py
examples/css_class_predicates.py
examples/derive_example.py
examples/namespace_example.py
examples/python_api_basic.py
examples/real_world_article.py
examples/xml_document_formatting.py
markuplift/__init__.py
markuplift/__main__.py
markuplift/annotation.py
markuplift/attribute_formatting.py
markuplift/cli.py
markuplift/doctype.py
markuplift/document_formatter.py
markuplift/empty_element.py
markuplift/escaping.py
markuplift/formatter.py
markuplift/html5_formatter.py
markuplift/namespace.py
markuplift/parsing.py
markuplift/predicates.py
markuplift/source_locator.py
markuplift/types.py
markuplift/utilities.py
markuplift/xml_formatter.py
markuplift-6.1.4.dist-info/licenses/LICENSE
markuplift-6.1.4.dist-info/METADATA
markuplift-6.1.4.dist-info/WHEEL
markuplift-6.1.4.dist-info/entry_points.txt
markuplift-6.1.4.dist-info/top_level.txt
markuplift-6.1.4.dist-info/RECORD
