Metadata-Version: 2.4
Name: markuplift
Version: 6.1.4
Summary: A configurable XML and HTML formatter.
Author-email: Robert Smallshire <robert@smallshire.org.uk>
License-Expression: MIT
Classifier: Development Status :: 5 - Production/Stable
Classifier: Intended Audience :: Developers
Classifier: Operating System :: OS Independent
Classifier: Programming Language :: Python :: 3
Classifier: Programming Language :: Python :: 3.12
Classifier: Programming Language :: Python :: 3.13
Classifier: Topic :: Software Development :: Libraries :: Python Modules
Classifier: Topic :: Text Processing :: Markup :: HTML
Classifier: Topic :: Text Processing :: Markup :: XML
Requires-Python: >=3.12
License-File: LICENSE
Requires-Dist: click>=8.2.1
Requires-Dist: html5lib>=1.1
Requires-Dist: jsbeautifier>=1.15.4
Requires-Dist: lxml>=6.0.1
Requires-Dist: pytest>=8.4.1
Requires-Dist: typename>=1.0.4
Dynamic: license-file
